{
  "images": [
    {
      "id": "1bea47ed-f6a9-463b-b423-14b9cca9ad27",
      "name": "cirros-0.6.2-x86_64",
      "status": "active",
      "visibility": "public",
      "size": 21430272,
      "virtual_size": null,
      "disk_format": "qcow2",
      "container_format": "bare",
      "checksum": "64d7c1cd2b6f60c92c14662941cb7913",
      "os_hash_algo": "sha512",
      "os_hash_value": "073b4523583784fbe01daff81eba092a262ec37ba6d04dd3f52e4cd8c",
      "min_disk": 0,
      "min_ram": 0,
      "protected": false,
      "owner": "263fd9e5069d4d47b26d3b4b3f13af18",
      "created_at": "2026-06-30T09:00:00Z",
      "updated_at": "2026-06-30T09:02:00Z",
      "tags": [],
      "file": "/v2/images/1bea47ed-f6a9-463b-b423-14b9cca9ad27/file",
      "schema": "/v2/schemas/image"
    },
    {
      "id": "781b3762-9469-4cec-b58d-3349e5de4e9c",
      "name": "ubuntu-22.04-server-cloudimg-amd64",
      "status": "active",
      "visibility": "shared",
      "size": 668991488,
      "virtual_size": 2361393152,
      "disk_format": "qcow2",
      "container_format": "bare",
      "checksum": "8a40c862b5735975d82605c1dd395796",
      "min_disk": 8,
      "min_ram": 512,
      "protected": false,
      "owner": "263fd9e5069d4d47b26d3b4b3f13af18",
      "created_at": "2026-07-01T09:00:00Z",
      "updated_at": "2026-07-01T09:05:00Z",
      "tags": ["lts"],
      "file": "/v2/images/781b3762-9469-4cec-b58d-3349e5de4e9c/file",
      "schema": "/v2/schemas/image"
    }
  ],
  "first": "/v2/images",
  "schema": "/v2/schemas/images"
}
